zap/__init__.py
zap/__main__.py
zap/album.py
zap/binaries.py
zap/no_album.png
zap/player.py
zap/pyinstaller_entry.py
zap/unknown_album.png
zap/zap.py
zap/zipped_album_icon.ico
zap/zipped_album_icon.png
zipped_album_player-0.6.5.dist-info/entry_points.txt
zipped_album_player-0.6.5.dist-info/licenses/LICENSE
zipped_album_player-0.6.5.dist-info/WHEEL
zipped_album_player-0.6.5.dist-info/METADATA
zipped_album_player-0.6.5.dist-info/RECORD
