Metadata-Version: 2.4
Name: Zipped-Album-Player
Version: 0.6.5
Summary: Zipped Album Player (ZAP) - A simple Python-based cross-platform player for the Zipped Album format
Author-email: Florian Krause <florian.krause@fladd.de>
Requires-Python: >=3.8
License-Expression: GPL-3.0-or-later
Classifier: Programming Language :: Python :: 3
Classifier: Operating System :: OS Independent
License-File: LICENSE
Requires-Dist: pillow>=7.0.0,<11.4
Requires-Dist: PyMuPDF>=1.17.4,<1.27
Requires-Dist: mutagen==1.47
Requires-Dist: pyglet>=2.0.10,<2.2
Requires-Dist: python-dateutil
Requires-Dist: tkinterdnd2
Requires-Dist: pyobjc-framework-Cocoa; sys_platform == 'darwin'
Project-URL: Bug Tracker, https://github.com/zipped-album/zap/issues
Project-URL: Homepage, https://zipped-album.github.io
Project-URL: Repository, https://github.com/zipped-album/zap.git
